raindrop_query/__init__.py
raindrop_query/_version.py
raindrop_query/basesdk.py
raindrop_query/conversations.py
raindrop_query/events.py
raindrop_query/httpclient.py
raindrop_query/py.typed
raindrop_query/sdk.py
raindrop_query/sdkconfiguration.py
raindrop_query/signal_groups.py
raindrop_query/signals.py
raindrop_query/users.py
raindrop_query/_hooks/__init__.py
raindrop_query/_hooks/registration.py
raindrop_query/_hooks/sdkhooks.py
raindrop_query/_hooks/types.py
raindrop_query/errors/__init__.py
raindrop_query/errors/conversations_getop.py
raindrop_query/errors/conversations_listop.py
raindrop_query/errors/events_facetsop.py
raindrop_query/errors/events_getop.py
raindrop_query/errors/events_listop.py
raindrop_query/errors/events_searchop.py
raindrop_query/errors/no_response_error.py
raindrop_query/errors/raindropquerydefaulterror.py
raindrop_query/errors/raindropqueryerror.py
raindrop_query/errors/responsevalidationerror.py
raindrop_query/errors/signal_groups_getop.py
raindrop_query/errors/signal_groups_list_signalsop.py
raindrop_query/errors/signal_groups_listop.py
raindrop_query/errors/signals_getop.py
raindrop_query/errors/signals_listop.py
raindrop_query/errors/users_getop.py
raindrop_query/errors/users_listop.py
raindrop_query/models/__init__.py
raindrop_query/models/conversations_getop.py
raindrop_query/models/conversations_listop.py
raindrop_query/models/events_countop.py
raindrop_query/models/events_facetsop.py
raindrop_query/models/events_getop.py
raindrop_query/models/events_listop.py
raindrop_query/models/events_searchop.py
raindrop_query/models/events_timeseriesop.py
raindrop_query/models/security.py
raindrop_query/models/signal_groups_getop.py
raindrop_query/models/signal_groups_list_signalsop.py
raindrop_query/models/signal_groups_listop.py
raindrop_query/models/signals_getop.py
raindrop_query/models/signals_listop.py
raindrop_query/models/users_getop.py
raindrop_query/models/users_listop.py
raindrop_query/types/__init__.py
raindrop_query-0.1.3.dist-info/METADATA
raindrop_query-0.1.3.dist-info/WHEEL
raindrop_query-0.1.3.dist-info/top_level.txt
raindrop_query-0.1.3.dist-info/RECORD
