Metadata-Version: 2.4
Name: raindrop-query
Version: 0.1.3
Summary: Official Python SDK for the Raindrop Query API
Author-email: Raindrop <support@raindrop.ai>
License: Apache-2.0
Requires-Python: >=3.9.2
Requires-Dist: httpcore>=1.0.9
Requires-Dist: httpx>=0.28.1
Requires-Dist: pydantic>=2.11.2
